jupyter_cadquery/__init__.py
jupyter_cadquery/_version.py
jupyter_cadquery/animation.py
jupyter_cadquery/base.py
jupyter_cadquery/cad_animation.py
jupyter_cadquery/cad_objects.py
jupyter_cadquery/defaults.py
jupyter_cadquery/export.py
jupyter_cadquery/logo.py
jupyter_cadquery/mp_tess.py
jupyter_cadquery/mp_tessellator.py
jupyter_cadquery/ocp_utils.py
jupyter_cadquery/progress.py
jupyter_cadquery/replay.py
jupyter_cadquery/serialize.py
jupyter_cadquery/stepreader.py
jupyter_cadquery/tessellator.py
jupyter_cadquery/tools.py
jupyter_cadquery/utils.py
jupyter_cadquery/cadquery/__init__.py
jupyter_cadquery/icons/dark/bottom.png
jupyter_cadquery/icons/dark/edges.png
jupyter_cadquery/icons/dark/empty.png
jupyter_cadquery/icons/dark/empty_mesh.png
jupyter_cadquery/icons/dark/empty_shape.png
jupyter_cadquery/icons/dark/fit.png
jupyter_cadquery/icons/dark/front.png
jupyter_cadquery/icons/dark/isometric.png
jupyter_cadquery/icons/dark/left.png
jupyter_cadquery/icons/dark/mesh.png
jupyter_cadquery/icons/dark/mix_mesh.png
jupyter_cadquery/icons/dark/mix_shape.png
jupyter_cadquery/icons/dark/no_mesh.png
jupyter_cadquery/icons/dark/no_shape.png
jupyter_cadquery/icons/dark/plane.png
jupyter_cadquery/icons/dark/rear.png
jupyter_cadquery/icons/dark/reset.png
jupyter_cadquery/icons/dark/right.png
jupyter_cadquery/icons/dark/shape.png
jupyter_cadquery/icons/dark/top.png
jupyter_cadquery/icons/light/bottom.png
jupyter_cadquery/icons/light/edges.png
jupyter_cadquery/icons/light/empty.png
jupyter_cadquery/icons/light/empty_mesh.png
jupyter_cadquery/icons/light/empty_shape.png
jupyter_cadquery/icons/light/fit.png
jupyter_cadquery/icons/light/front.png
jupyter_cadquery/icons/light/isometric.png
jupyter_cadquery/icons/light/left.png
jupyter_cadquery/icons/light/mesh.png
jupyter_cadquery/icons/light/mix_mesh.png
jupyter_cadquery/icons/light/mix_shape.png
jupyter_cadquery/icons/light/no_mesh.png
jupyter_cadquery/icons/light/no_shape.png
jupyter_cadquery/icons/light/plane.png
jupyter_cadquery_orion-0.0.1.dist-info/LICENSE
jupyter_cadquery_orion-0.0.1.dist-info/METADATA
jupyter_cadquery_orion-0.0.1.dist-info/WHEEL
jupyter_cadquery_orion-0.0.1.dist-info/top_level.txt
jupyter_cadquery_orion-0.0.1.dist-info/RECORD
