Metadata-Version: 2.1
Name: jupyter-cadquery-orion
Version: 0.0.1
Summary: An extension to render cadquery objects in JupyterLab via pythreejs
Home-page: https://github.com/bernhard-42/jupyter-cadquery
Author: Bernhard Walter
Author-email: b_walter@arcor.de
License: UNKNOWN
Keywords: ipython,jupyter,widgets,CAD,cadquery
Platform: UNKNOWN
Classifier: Development Status :: 5 - Production/Stable
Classifier: Framework :: IPython
Classifier: Intended Audience :: Developers
Classifier: Intended Audience :: Science/Research
Classifier: Topic :: Multimedia :: Graphics
Classifier: Programming Language :: Python :: 3
Classifier: Programming Language :: Python :: 3.7
Classifier: Programming Language :: Python :: 3.8
Classifier: Programming Language :: Python :: 3.9
Requires-Python: >=3.6
License-File: LICENSE
Requires-Dist: webcolors ~=1.12
Requires-Dist: voila ~=0.3.5
Requires-Dist: numpy-quaternion ==2023.0.4
Requires-Dist: cad-viewer-widget ~=1.4.0
Requires-Dist: cachetools ~=5.2.0
Provides-Extra: dev
Requires-Dist: pyYaml ; extra == 'dev'
Requires-Dist: black ; extra == 'dev'
Requires-Dist: jupyter-packaging ; extra == 'dev'
Requires-Dist: pylint ; extra == 'dev'
Requires-Dist: bumpversion ; extra == 'dev'
Requires-Dist: cookiecutter ; extra == 'dev'
Requires-Dist: twine ; extra == 'dev'
